git_code_debt/__init__.py
git_code_debt/discovery.py
git_code_debt/file_diff_stat.py
git_code_debt/generate.py
git_code_debt/generate_config.py
git_code_debt/list_metrics.py
git_code_debt/logic.py
git_code_debt/metric.py
git_code_debt/options.py
git_code_debt/repo_parser.py
git_code_debt/write_logic.py
git_code_debt/metrics/__init__.py
git_code_debt/metrics/base.py
git_code_debt/metrics/binary_file_count.py
git_code_debt/metrics/common.py
git_code_debt/metrics/curse.py
git_code_debt/metrics/curse_words.py
git_code_debt/metrics/imports.py
git_code_debt/metrics/lines.py
git_code_debt/metrics/lines_in_init.py
git_code_debt/metrics/submodule_count.py
git_code_debt/metrics/symlink_count.py
git_code_debt/metrics/todo.py
git_code_debt/schema/metric_changes.sql
git_code_debt/schema/metric_data.sql
git_code_debt/schema/metric_names.sql
git_code_debt/server/__init__.py
git_code_debt/server/app.py
git_code_debt/server/logic.py
git_code_debt/server/metric_config.py
git_code_debt/server/metric_config.sample.yaml
git_code_debt/server/render_mako.py
git_code_debt/server/presentation/__init__.py
git_code_debt/server/presentation/commit_delta.py
git_code_debt/server/presentation/delta.py
git_code_debt/server/servlets/__init__.py
git_code_debt/server/servlets/changes.py
git_code_debt/server/servlets/commit.py
git_code_debt/server/servlets/graph.py
git_code_debt/server/servlets/index.py
git_code_debt/server/servlets/status.py
git_code_debt/server/servlets/widget.py
git_code_debt/server/static/css/git_code_debt.css
git_code_debt/server/static/img/loading.gif
git_code_debt/server/static/js/graph.js
git_code_debt/server/static/js/index.js
git_code_debt/server/static/js/jquery.flot.min.js
git_code_debt/server/static/js/jquery.flot.selection.min.js
git_code_debt/server/static/js/jquery.flot.time.min.js
git_code_debt/server/static/js/widget.js
git_code_debt/server/static/js/widget_frame.js
git_code_debt/server/templates/base.mako
git_code_debt/server/templates/changes.mako
git_code_debt-1.2.0.dist-info/LICENSE
git_code_debt-1.2.0.dist-info/METADATA
git_code_debt-1.2.0.dist-info/WHEEL
git_code_debt-1.2.0.dist-info/entry_points.txt
git_code_debt-1.2.0.dist-info/top_level.txt
git_code_debt-1.2.0.dist-info/RECORD
