Metadata-Version: 2.1
Name: git_code_debt
Version: 1.2.0
Summary: A dashboard for monitoring code debt in a git repository.
Home-page: https://github.com/asottile/git-code-debt
Author: Anthony Sottile
Author-email: asottile@umich.edu
License: MIT
Classifier: Programming Language :: Python :: 3
Classifier: Programming Language :: Python :: 3 :: Only
Classifier: Programming Language :: Python :: Implementation :: CPython
Classifier: Programming Language :: Python :: Implementation :: PyPy
Requires-Python: >=3.10
License-File: LICENSE
Requires-Dist: cfgv
Requires-Dist: flask
Requires-Dist: identify
Requires-Dist: mako
Requires-Dist: markdown-code-blocks
Requires-Dist: pyyaml
